<?xml version="1.0" encoding="UTF-8"?>
<entity xmlns:xsi="http://www.w3.org/2001/XMLSchema-instance" name="IUserMarket" remark="" schema="JD" table="I_USER_MARKET" xsi:noNamespaceSchemaLocation="http://10.10.10.141/easyframe/schema/entity.xsd">
    <fields>
        <field column="USER_ID" columnDef="BigInt" name="userId" primitive="No" remark="" type="Long"/>
        <field column="PRODUCT_ID" columnDef="BigInt" name="productId" primitive="No" remark="" type="Long"/>
        <field column="BUSI_TYPE" columnDef="Int" name="busiType" primitive="No" remark="" type="Integer"/>
        <field column="SP_TYPE" columnDef="Int" name="spType" primitive="No" remark="" type="Integer"/>
        <field column="SP_CODE" columnDef="BigInt" name="spCode" primitive="No" remark="" type="Long"/>
        <field column="OPERATOR_CODE" columnDef="Varchar" columnSize="32" name="operatorCode" primitive="No" remark="" type="String"/>
        <field column="SERVICE_CODE" columnDef="Varchar" columnSize="32" name="serviceCode" primitive="No" remark="" type="String"/>
        <field column="REGION_CODE" columnDef="Int" name="regionCode" primitive="No" remark="" type="Integer"/>
        <field column="EXTEND1" columnDef="Varchar" name="extend1" columnSize="32" primitive="No" remark="" type="String"/>
        <field column="EXTEND2" columnDef="Varchar" name="extend2" columnSize="64" primitive="No" remark="" type="String"/>
        <field column="REMARK" columnDef="Varchar" name="remark" columnSize="255" primitive="No" remark="" type="String"/>
        
        <field column="VALID_DATE" columnDef="TimeStamp" name="validDate" primitive="No" remark="" type="Date"/>
        <field column="EXPIRE_DATE" columnDef="TimeStamp" name="expireDate" primitive="No" remark="" type="Date"/>
        <field column="OPER_TYPE" columnDef="Int" name="operType" primitive="No" remark="" type="Integer"/>
        <field column="SO_NBR" columnDef="BigInt" name="soNbr" primitive="No" remark="" type="Long"/>
        <field column="COMMIT_DATE" columnDef="TimeStamp" name="commitDate" primitive="No" remark="" type="Date"/>
    </fields>
</entity>
