<?xml version="1.0" encoding="UTF-8" standalone="no"?>
<entity xsi:noNamespaceSchemaLocation="http://10.10.10.141/easyframe/schema/entity.xsd" name="UserQueryReq">
  <root ref="imsinner.BaseQueryReq"/>
  <fields>
    <complex-field name="userIds" type="Long" collection="list" primitive="false"/>
    <complex-field name="phoneIds" type="String" collection="list" primitive="false"/>
    <field name="isCmResLifeCycle" type="Boolean" isPk="false" primitive="Auto" null-able="true"/>
    <field name="isCmResIdentity" type="Boolean" isPk="false" primitive="Auto" null-able="true"/>
    <field name="isCmIdentityVsImei" type="Boolean" isPk="false" primitive="Auto" null-able="true"/>
    <field name="isCmResExt" type="Boolean" isPk="false" primitive="Auto" null-able="true"/>
    <field name="isBillAcctId" type="Boolean" isPk="false" primitive="Auto" null-able="true"/>
    <field name="isUserBudget" type="Boolean" isPk="false" primitive="Auto" null-able="true"/>
    <field name="isMainPromotion" type="Boolean" isPk="false" primitive="Auto" null-able="true"/>
    <field name="isCmResource" type="Boolean" isPk="false" primitive="Auto" null-able="true"/>
    <field name="isValidtity" type="Boolean" isPk="false" primitive="Auto" null-able="true"/>
  </fields>
</entity>