<?xml version="1.0" encoding="UTF-8"?>
<entity xmlns:xsi="http://www.w3.org/2001/XMLSchema-instance" name="SLifeCycleOncePreNotify" remark="" sdl="true" sdl-module="MImsTsDef" xsi:noNamespaceSchemaLocation="http://10.10.10.149/easyframe/schema/entity.xsd">
    <fields>
        <field name="resourceId" primitive="Yes" remark="" sdl="true" type="Long"/>
        <field name="notifyDate" primitive="Yes" remark="" sdl="true" type="Date"/>
        <field name="notifyCount" primitive="Yes" remark="" sdl="true" type="Integer"/>
        <field name="modifyDate" primitive="Yes" remark="" sdl="true" type="Date"/>
        <field name="retryTimes" primitive="Yes" remark="" sdl="true" type="Integer"/>
        <field name="sts" primitive="Yes" remark="" sdl="true" type="Integer"/>
        <field name="nsts" primitive="Yes" remark="" sdl="true" type="Integer"/>
        <field name="psts" primitive="Yes" remark="" sdl="true" type="Integer"/>
    </fields>
</entity>
